.pypirc
LICENSE.GPL
LICENSE.txt
MANIFEST.in
README.txt
bootstrap.py
buildout.cfg
distribute-0.6.24.tar.gz
setup.py
test-plone-4.0.x.cfg
Products/__init__.py
Products.PloneOntology.egg-info/PKG-INFO
Products.PloneOntology.egg-info/SOURCES.txt
Products.PloneOntology.egg-info/dependency_links.txt
Products.PloneOntology.egg-info/entry_points.txt
Products.PloneOntology.egg-info/namespace_packages.txt
Products.PloneOntology.egg-info/not-zip-safe
Products.PloneOntology.egg-info/requires.txt
Products.PloneOntology.egg-info/top_level.txt
Products/PloneOntology/__init__.py
Products/PloneOntology/archive.py
Products/PloneOntology/config.py
Products/PloneOntology/configure.zcml
Products/PloneOntology/ctool.py
Products/PloneOntology/graphviztool.py
Products/PloneOntology/keyword.py
Products/PloneOntology/keywordgraph.py
Products/PloneOntology/kwStorageView.pt
Products/PloneOntology/ontology.py
Products/PloneOntology/owl.py
Products/PloneOntology/poapi.py
Products/PloneOntology/profiles.zcml
Products/PloneOntology/proposal.py
Products/PloneOntology/setuphandlers.py
Products/PloneOntology/storage.gif
Products/PloneOntology/storage.png
Products/PloneOntology/tool.gif
Products/PloneOntology/tool.png
Products/PloneOntology/utils.py
Products/PloneOntology/widget.py
Products/PloneOntology/Extensions/Install.py
Products/PloneOntology/doc/PloneOntology.pdf
Products/PloneOntology/doc/beer.owl
Products/PloneOntology/doc/demoOntologie.owl
Products/PloneOntology/doc/talk.pdf
Products/PloneOntology/i18n/Ontology-es.po
Products/PloneOntology/i18n/Ontology-plone-es.po
Products/PloneOntology/i18n/Ontology-plone-pt-br.po
Products/PloneOntology/i18n/Ontology-plone.pot
Products/PloneOntology/i18n/Ontology-pt-br.po
Products/PloneOntology/i18n/Ontology.pot
Products/PloneOntology/profiles/default/actionicons.xml
Products/PloneOntology/profiles/default/actions.xml
Products/PloneOntology/profiles/default/catalog.xml
Products/PloneOntology/profiles/default/controlpanel.xml
Products/PloneOntology/profiles/default/import_steps.xml
Products/PloneOntology/profiles/default/metadata.xml
Products/PloneOntology/profiles/default/propertiestool.xml
Products/PloneOntology/profiles/default/skins.xml
Products/PloneOntology/profiles/default/toolset.xml
Products/PloneOntology/profiles/default/types.xml
Products/PloneOntology/profiles/default/workflows.xml
