Metadata-Version: 1.0
Name: Products.PloneOntology
Version: 1.0.0
Summary: A discussion board for Plone.
Home-page: https://github.com/collective/Products.PloneOntology
Author: Alex Clark
Author-email: aclark@aclark.net
License: GPL
Keywords: Plone Ontology OWL
Platform: UNKNOWN
Classifier: Framework :: Plone
Classifier: Framework :: Zope2
Classifier: Programming Language :: Python
